taiga_contrib_openid_auth/__init__.py
taiga_contrib_openid_auth/apps.py
taiga_contrib_openid_auth/connector.py
taiga_contrib_openid_auth/services.py
taiga_contrib_openid_auth-0.0.1.dist-info/LICENSE
taiga_contrib_openid_auth-0.0.1.dist-info/METADATA
taiga_contrib_openid_auth-0.0.1.dist-info/WHEEL
taiga_contrib_openid_auth-0.0.1.dist-info/top_level.txt
taiga_contrib_openid_auth-0.0.1.dist-info/RECORD
